{
  "quiz_id": "system-design-m1-t3-quiz",
  "questions": [
    {
      "question_id": "q1",
      "text": "What is the key optimization criteria for Network Routing?",
      "options": [
        "Minimizing complexity bounds.",
        "Increasing CPU utilization.",
        "Static heap allocation.",
        "Syntax execution bypass."
      ],
      "correct_answer": "Minimizing complexity bounds.",
      "explanation": "The primary goal in designing Network Routing is minimizing asymptotic and memory complexities."
    }
  ]
}